esther_cmd/__init__.py
esther_cmd/cmd.py
esther_cmd-0.1.1.dist-info/METADATA
esther_cmd-0.1.1.dist-info/WHEEL
esther_cmd-0.1.1.dist-info/entry_points.txt
esther_cmd-0.1.1.dist-info/top_level.txt
esther_cmd-0.1.1.dist-info/RECORD
