Metadata-Version: 2.1
Name: esther_cmd
Version: 0.1.1
Summary: Default template for PDM package
Author-email: EstherCho-7 <dkgkqm777@gmail.com>
License: MIT
Requires-Python: >=3.9
Requires-Dist: esther-lotto >=0.2.0
